suitesparse_amd/__init__.py
suitesparse_amd/_amd.c
suitesparse_amd/_amd.cpython-313-x86_64-linux-android.so
suitesparse_amd/_amd.pyi
suitesparse_amd/amd.py
suitesparse_amd/amd.pyi
suitesparse_amd/py.typed
suitesparse_amd-0.3.5.dist-info/licenses/LICENSE
suitesparse_amd-0.3.5.dist-info/METADATA
suitesparse_amd-0.3.5.dist-info/WHEEL
suitesparse_amd-0.3.5.dist-info/top_level.txt
suitesparse_amd-0.3.5.dist-info/RECORD
