Metadata-Version: 2.4
Name: suitesparse-amd
Version: 0.3.5
Summary: A Python wrapper for the C-Library for SuiteSparse's Approximate Minimum Degree (AMD) algorithm
Author-email: Marius Juston <marius.juston@hotmail.fr>
License-Expression: MIT
Project-URL: Homepage, https://github.com/Marius-Juston/SuiteSparse
Project-URL: Issues, https://github.com/Marius-Juston/SuiteSparse/issues
Keywords: suitesparse,amd,sparse,approximate minimum degree
Classifier: Programming Language :: Python :: 3
Classifier: Programming Language :: Python
Classifier: Operating System :: OS Independent
Requires-Python: >=3.10
License-File: LICENSE
Provides-Extra: dev
Requires-Dist: black; extra == "dev"
Requires-Dist: bumpver; extra == "dev"
Requires-Dist: isort; extra == "dev"
Requires-Dist: pip-tools; extra == "dev"
Requires-Dist: pytest; extra == "dev"
Dynamic: license-file
